setup.cfg
setup.py
acdcreatereal/__init__.py
acdcreatereal/acdcreatereal.py
acdcreatereal.egg-info/PKG-INFO
acdcreatereal.egg-info/SOURCES.txt
acdcreatereal.egg-info/dependency_links.txt
acdcreatereal.egg-info/requires.txt
acdcreatereal.egg-info/top_level.txt