Metadata-Version: 2.1
Name: acdcreatereal
Version: 0.1
Summary: Быстрая библиотека для создания файлов | Версия для создания файлов с реальным размером!
Home-page: UNKNOWN
Author: Sasibacka
Author-email: sergeycikkatkovcik@gmail.com
License: UNKNOWN
Platform: UNKNOWN
